annovahj/__init__.py
annovahj/anovatest.py
hjannova-0.0.2.dist-info/LICENSE
hjannova-0.0.2.dist-info/METADATA
hjannova-0.0.2.dist-info/WHEEL
hjannova-0.0.2.dist-info/top_level.txt
hjannova-0.0.2.dist-info/RECORD
