Metadata-Version: 2.1
Name: hjannova
Version: 0.0.2
Summary: ANOVA TEST
Home-page: UNKNOWN
Author: Harshwardhan Jadhav
Author-email: harshwardhanpj2001@gmail.com
License: UNKNOWN
Keywords: annovatest,feature selection,annova test,python tutorial,hj annova test
Platform: UNKNOWN
Classifier: Development Status :: 1 - Planning
Classifier: Intended Audience :: Developers
Classifier: Programming Language :: Python :: 3.10
Classifier: Operating System :: Unix
Classifier: Operating System :: MacOS :: MacOS X
Classifier: Operating System :: Microsoft :: Windows
Requires-Dist: scipy
